src/ALU_sel.sv
//////////////////////////////////////////////////////////////////////////////////
// Company: ITESO
// Engineer: Jorge Alberto Padilla Gutierrez
// Module Description: RISC-V ALU definitions
//////////////////////////////////////////////////////////////////////////////////

`define SEL_ADD     5'b00000
`define SEL_SUB	    5'b10000
`define SEL_XOR	    5'b00100
`define SEL_OR      5'b00110
`define SEL_AND	    5'b00111
`define SEL_SLL	    5'b00001
`define SEL_SRL	    5'b00101
`define SEL_SRA	    5'b10101
`define SEL_SLT	    5'b00010
`define SEL_SLTU	5'b00011
`define SEL_MUL     5'b01000

src/ALU.sv
//////////////////////////////////////////////////////////////////////////////////
// Company: ITESO
// Engineer: Jorge Alberto Padilla Gutierrez
// Module Description: RISC-V ALU
//////////////////////////////////////////////////////////////////////////////////

`include "ALU_sel.sv"

module ALU(
	//Inputs
	input[31:0]			a,
	input[31:0]			b,
	input[4:0]			sel,
	//Outputs
	output reg[31:0]	f,
	output reg			z
);

	//Combinational Always
	always @(*)
	begin
		//Selector
		case (sel)
			`SEL_ADD	: f = a + b;											//add
			`SEL_SUB	: f = a - b;											//sub
			`SEL_XOR	: f = a ^ b;											//xor
			`SEL_OR		: f = a | b;											//or
			`SEL_AND	: f = a & b;											//and
			`SEL_SLL	: f = a << b;											//sll
			`SEL_SRL	: f = a >> b;											//srl
			`SEL_SRA	: f = signed'(a) >>> b;									//sra
			`SEL_SLT	: f = (signed'(a) < signed'(b)) ? 32'h1 : 32'h0;		//slt
			`SEL_SLTU	: f = (unsigned'(a) < unsigned'(b)) ? 32'h1 : 32'h0;	//sltu
			`SEL_MUL	: f = a * b;											//mul
			default		: f = 32'h0;
		endcase
		//Zero flag
		if (f == 0)
			z = 1'b1;
		else
			z = 1'b0;
	end
	
endmodule

src/ALU_tb.sv
//////////////////////////////////////////////////////////////////////////////////
// Company: ITESO
// Engineer: Jorge Alberto Padilla Gutierrez
// Module Description: RISC-V ALU Testbench
//////////////////////////////////////////////////////////////////////////////////

module ALU_tb;
	//DUT variables
	reg[31:0]   a_tb;
    reg[31:0]   b_tb;
	reg[4:0]    sel_tb;
	wire[31:0]  f_tb;
	wire        z_tb;
	
	//DUT Instance
	ALU DUT(
		.a(a_tb), .b(b_tb), .sel(sel_tb), .f(f_tb), .z(z_tb)
	);
	
	reg[4:0] stimulus;
	
	initial
		begin
	
		$dumpfile("dump.vcd");
		$dumpvars(1);
		
		a_tb = 32'h0000000F;
		b_tb = 32'h00000003;
		
		for(stimulus = 0; stimulus < 8; stimulus = stimulus + 1)
		begin
			sel_tb = stimulus;
			#1;
		end
			
        sel_tb = 5'b10000;
		#1;
        sel_tb = 5'b10101;
		#1;
        sel_tb = 5'b01000;
		#1;
		
		a_tb = 32'hF000000F;
		b_tb = 32'h00000003;
		
		for(stimulus = 0; stimulus < 8; stimulus = stimulus + 1)
		begin
			sel_tb = stimulus;
			#1;
		end
			
        sel_tb = 5'b10000;
		#1;
        sel_tb = 5'b10101;
		#1;
        sel_tb = 5'b01000;
		#1;
		
		a_tb = 32'h01234567;
		b_tb = 32'h89ABCDEF;
		
		for(stimulus = 0; stimulus < 8; stimulus = stimulus + 1)
		begin
			sel_tb = stimulus;
			#1;
		end
			
        sel_tb = 5'b10000;
		#1;
        sel_tb = 5'b10101;
		#1;
        sel_tb = 5'b01000;
		#1;
		
		a_tb = 32'h00000000;
		b_tb = 32'h00000000;
		
		for(stimulus = 0; stimulus < 8; stimulus = stimulus + 1)
		begin
			sel_tb = stimulus;
			#1;
		end
			
        sel_tb = 5'b10000;
		#1;
        sel_tb = 5'b10101;
		#1;
        sel_tb = 5'b01000;
		#1;
		
		a_tb = 32'hFFFFFFFF;
		b_tb = 32'hFFFFFFFF;
		
		for(stimulus = 0; stimulus < 8; stimulus = stimulus + 1)
		begin
			sel_tb = stimulus;
			#1;
		end

        sel_tb = 5'b10000;
		#1;
        sel_tb = 5'b10101;
		#1;
        sel_tb = 5'b01000;
		#1;
		
		$finish;
		end
endmodule

val/dump.vcd
$date
	Tue Feb 21 10:05:12 2023
$end
$version
	Questa Intel Starter FPGA Edition Version 2021.2
$end
$timescale
	1ns
$end

$scope module ALU_tb $end
$var reg 32 ! a_tb [31:0] $end
$var reg 32 " b_tb [31:0] $end
$var reg 5 # sel_tb [4:0] $end
$var wire 1 $ f_tb [31] $end
$var wire 1 % f_tb [30] $end
$var wire 1 & f_tb [29] $end
$var wire 1 ' f_tb [28] $end
$var wire 1 ( f_tb [27] $end
$var wire 1 ) f_tb [26] $end
$var wire 1 * f_tb [25] $end
$var wire 1 + f_tb [24] $end
$var wire 1 , f_tb [23] $end
$var wire 1 - f_tb [22] $end
$var wire 1 . f_tb [21] $end
$var wire 1 / f_tb [20] $end
$var wire 1 0 f_tb [19] $end
$var wire 1 1 f_tb [18] $end
$var wire 1 2 f_tb [17] $end
$var wire 1 3 f_tb [16] $end
$var wire 1 4 f_tb [15] $end
$var wire 1 5 f_tb [14] $end
$var wire 1 6 f_tb [13] $end
$var wire 1 7 f_tb [12] $end
$var wire 1 8 f_tb [11] $end
$var wire 1 9 f_tb [10] $end
$var wire 1 : f_tb [9] $end
$var wire 1 ; f_tb [8] $end
$var wire 1 < f_tb [7] $end
$var wire 1 = f_tb [6] $end
$var wire 1 > f_tb [5] $end
$var wire 1 ? f_tb [4] $end
$var wire 1 @ f_tb [3] $end
$var wire 1 A f_tb [2] $end
$var wire 1 B f_tb [1] $end
$var wire 1 C f_tb [0] $end
$var wire 1 D z_tb $end
$var reg 5 E stimulus [4:0] $end
$upscope $end
$enddefinitions $end
#0
$dumpvars
b1111 !
b11 "
b0 #
b0 E
0C
1B
0A
0@
1?
0>
0=
0<
0;
0:
09
08
07
06
05
04
03
02
01
00
0/
0.
0-
0,
0+
0*
0)
0(
0'
0&
0%
0$
0D
$end
#1
b1 E
b1 #
0B
1@
1>
1=
#2
b10 E
b10 #
0@
0?
0>
0=
1D
#3
b11 E
b11 #
#4
b100 E
b100 #
1A
1@
0D
#5
b101 E
b101 #
1C
0A
0@
#6
b110 E
b110 #
1B
1A
1@
#7
b111 E
b111 #
0A
0@
#8
b1000 E
b10000 #
0C
0B
1A
1@
#9
b10101 #
1C
0A
0@
#10
b1000 #
1A
1@
1>
#11
b11110000000000000000000000001111 !
b0 E
b0 #
0C
1B
0A
0@
1?
0>
1'
1&
1%
1$
#12
b1 E
b1 #
0B
1@
1>
1=
0'
0&
0%
#13
b10 E
b10 #
1C
0@
0?
0>
0=
0$
#14
b11 E
b11 #
0C
1D
#15
b100 E
b100 #
1A
1@
1'
1&
1%
1$
0D
#16
b101 E
b101 #
1C
0A
0@
1*
1)
1(
0&
0%
0$
#17
b110 E
b110 #
1B
1A
1@
0*
0)
0(
1&
1%
1$
#18
b111 E
b111 #
0A
0@
0'
0&
0%
0$
#19
b1000 E
b10000 #
0C
0B
1A
1@
1'
1&
1%
1$
#20
b10101 #
1C
0A
0@
1*
1)
1(
#21
b1000 #
1A
1@
1>
0*
0)
0(
0&
#22
b1001000110100010101100111 !
b10001001101010111100110111101111 "
b0 E
b0 #
0C
1B
0@
1?
0>
1=
1;
1:
17
13
12
11
10
1-
1,
1*
1(
0'
0%
#23
b1 E
b1 #
0B
0A
0?
0=
0;
0:
07
03
02
01
00
0-
0,
0*
0(
0$
1D
#24
b10 E
b10 #
#25
b11 E
b11 #
1C
0D
#26
b100 E
b100 #
0C
1@
1<
18
14
10
1,
1(
1$
#27
b101 E
b101 #
0@
0<
08
04
00
0,
0(
0$
1D
#28
b110 E
b110 #
1C
1B
1A
1@
1>
1=
1<
1;
19
18
15
14
13
12
10
1.
1,
1+
1(
1$
0D
#29
b111 E
b111 #
0@
0<
08
04
00
0,
0(
0$
#30
b1000 E
b10000 #
0C
0B
0A
1@
1?
1:
17
16
11
1/
1-
1*
1)
1'
1&
1%
#31
b10101 #
0@
0?
0>
0=
0;
0:
09
07
06
05
03
02
01
0/
0.
0-
0+
0*
0)
0'
0&
0%
1D
#32
b1000 #
1C
1@
1>
1:
19
15
12
11
10
1-
1+
1(
1%
1$
0D
#33
b0 !
b0 "
b0 E
b0 #
0C
0@
0>
0:
09
05
02
01
00
0-
0+
0(
0%
0$
1D
#34
b1 E
b1 #
#35
b10 E
b10 #
#36
b11 E
b11 #
#37
b100 E
b100 #
#38
b101 E
b101 #
#39
b110 E
b110 #
#40
b111 E
b111 #
#41
b1000 E
b10000 #
#42
b10101 #
#43
b1000 #
#44
b11111111111111111111111111111111 !
b11111111111111111111111111111111 "
b0 E
b0 #
1B
1A
1@
1?
1>
1=
1<
1;
1:
19
18
17
16
15
14
13
12
11
10
1/
1.
1-
1,
1+
1*
1)
1(
1'
1&
1%
1$
0D
#45
b1 E
b1 #
0B
0A
0@
0?
0>
0=
0<
0;
0:
09
08
07
06
05
04
03
02
01
00
0/
0.
0-
0,
0+
0*
0)
0(
0'
0&
0%
0$
1D
#46
b10 E
b10 #
#47
b11 E
b11 #
#48
b100 E
b100 #
#49
b101 E
b101 #
#50
b110 E
b110 #
1C
1B
1A
1@
1?
1>
1=
1<
1;
1:
19
18
17
16
15
14
13
12
11
10
1/
1.
1-
1,
1+
1*
1)
1(
1'
1&
1%
1$
0D
#51
b111 E
b111 #
#52
b1000 E
b10000 #
0C
0B
0A
0@
0?
0>
0=
0<
0;
0:
09
08
07
06
05
04
03
02
01
00
0/
0.
0-
0,
0+
0*
0)
0(
0'
0&
0%
0$
1D
#53
b10101 #
1C
1B
1A
1@
1?
1>
1=
1<
1;
1:
19
18
17
16
15
14
13
12
11
10
1/
1.
1-
1,
1+
1*
1)
1(
1'
1&
1%
1$
0D
#54
b1000 #
0B
0A
0@
0?
0>
0=
0<
0;
0:
09
08
07
06
05
04
03
02
01
00
0/
0.
0-
0,
0+
0*
0)
0(
0'
0&
0%
0$
